pwdpy/__init__.py
pwdpy/cli_args.py
pwdpy/contants.py
pwdpy/pwdpy.py
pwdpy/strings/__init__.py
pwdpy/strings/strings.py
tests/__init__.py
tests/test_pwdpy.py
pwdpy-1.0.1.dist-info/LICENSE
pwdpy-1.0.1.dist-info/METADATA
pwdpy-1.0.1.dist-info/WHEEL
pwdpy-1.0.1.dist-info/entry_points.txt
pwdpy-1.0.1.dist-info/top_level.txt
pwdpy-1.0.1.dist-info/RECORD
