Metadata-Version: 2.1
Name: pwdpy
Version: 1.0.1
Summary: Password Tools
Author: Isaac Araujo
Author-email: <zac.araujo2001@gmail.com>
License: MIT License
Project-URL: Source, https://github.com/isaac-araujo/pwdpy
Keywords: python,password,password generator,password tools
Classifier: Development Status :: 4 - Beta
Classifier: Intended Audience :: Developers
Classifier: Programming Language :: Python :: 3.7
Classifier: Programming Language :: Python :: 3.8
Classifier: Programming Language :: Python :: 3.9
Classifier: Programming Language :: Python :: 3.10
Classifier: Operating System :: Unix
Classifier: Operating System :: MacOS :: MacOS X
Classifier: Operating System :: Microsoft :: Windows
License-File: LICENSE
